gpulink_sdk/__init__.py
gpulink_sdk/client.py
gpulink_sdk/constants.py
gpulink_sdk/py.typed
gpulink_sdk-0.0.1.dist-info/METADATA
gpulink_sdk-0.0.1.dist-info/WHEEL
gpulink_sdk-0.0.1.dist-info/licenses/LICENSE
gpulink_sdk-0.0.1.dist-info/RECORD
