Metadata-Version: 2.4
Name: gpulink-sdk
Version: 0.0.1
Summary: A lightweight Python SDK for interacting with GPULINK
Project-URL: Homepage, https://gpulink.org
Project-URL: Repository, https://github.com/gpulink-org/gpulink-sdk
Author-email: GPULINK <support@gpulink.org>
License: MIT License
License-File: LICENSE
Classifier: License :: OSI Approved :: MIT License
Classifier: Operating System :: OS Independent
Classifier: Programming Language :: Python :: 3
Classifier: Typing :: Typed
Requires-Python: >=3.11
Requires-Dist: httpx==0.28.1
Requires-Dist: websockets==15.0.1
